{
  "content": "## Core Wrapper Types\n\n### 1. ObjectWrapper\n\nThe base wrapper that provides common functionality for all wrapped objects:\n\n```java\npublic interface ObjectWrapper {\n  // Presence check\n  boolean isPresent();\n  \n  // Get underlying object\n  Object unwrap();\n  \n  // Property access\n  Set<String> getKeys();\n  ObjectWrapper get(String key);\n  \n  // Type conversion\n  String asString();\n  Integer asInteger();\n  BigDecimal asDecimal();\n  Boolean asBoolean();\n  Date asDate();\n  ListWrapper asList();\n  MapWrapper asMap();\n  \n  // Default values\n  String asString(String defaultValue);\n  Integer asInteger(Integer defaultValue);\n  // ...\n}\n```\n\n### 2. InfonodeWrapper\n\nWraps objects from the CD (Customer Data) system:",
  "metadata": {
    "source": "docs/md/03_Object_Wrappers.md",
    "relative_path": "docs/md/03_Object_Wrappers.md",
    "filename": "03_Object_Wrappers.md",
    "filetype": "md",
    "chunk_index": 3,
    "total_chunks": 24
  }
}